{
  "eyebrow": "Open-source contribution opportunity",
  "title": "Contribute to GENMRKT",
  "lede": "Contribute to an open-source project that ships public-good software.",
  "highLevelScopeTitle": "Where you can contribute this quarter",
  "scopeChips": [
    "Open-source agent workflows",
    "Governance-first scaffolds",
    "Project ops automation",
    "Docs + demos that teach"
  ],
  "impactTitle": "Contribution impact",
  "impactOneLiner": "You ship tools that help people learn and build safely.",
  "ctaLabel": "Apply to contribute",
  "ctaHref": "https://genmrkt.lovable.app/",
  "secondaryLinkLabel": "",
  "secondaryLinkHref": "",
  "finePrint": ""
}
